matrix_admin_sdk/__init__.py
matrix_admin_sdk/client.py
matrix_admin_sdk/endpoints/__init__.py
matrix_admin_sdk/endpoints/endpoint.py
matrix_admin_sdk/endpoints/v1/__init__.py
matrix_admin_sdk/endpoints/v1/account_validity.py
matrix_admin_sdk/endpoints/v1/background_updates.py
matrix_admin_sdk/endpoints/v1/delete_group.py
matrix_admin_sdk/endpoints/v1/delete_local_media.py
matrix_admin_sdk/endpoints/v1/edit_room_membership.py
matrix_admin_sdk/endpoints/v1/endpoint.py
matrix_admin_sdk/endpoints/v1/event_reports.py
matrix_admin_sdk/endpoints/v1/federation.py
matrix_admin_sdk/endpoints/v1/forward_extremities.py
matrix_admin_sdk/endpoints/v1/purge_history.py
matrix_admin_sdk/endpoints/v1/purge_remote_media.py
matrix_admin_sdk/endpoints/v1/quarantine_media.py
matrix_admin_sdk/endpoints/v1/querying_media.py
matrix_admin_sdk/endpoints/v1/register_user.py
matrix_admin_sdk/endpoints/v1/registration_tokens.py
matrix_admin_sdk/endpoints/v1/rooms.py
matrix_admin_sdk/endpoints/v1/server.py
matrix_admin_sdk/endpoints/v1/server_notices.py
matrix_admin_sdk/endpoints/v1/user.py
matrix_admin_sdk/endpoints/v1/user_media_statistics.py
matrix_admin_sdk/endpoints/v1/user_rate_limits.py
matrix_admin_sdk/endpoints/v2/__init__.py
matrix_admin_sdk/endpoints/v2/endpoint.py
matrix_admin_sdk/endpoints/v2/rooms.py
matrix_admin_sdk/endpoints/v2/user_devices.py
matrix_admin_sdk/endpoints/v2/users.py
matrix_admin_sdk/models/__init__.py
matrix_admin_sdk/models/base_model.py
matrix_admin_sdk/models/v1/__init__.py
matrix_admin_sdk/models/v1/account_validity.py
matrix_admin_sdk/models/v1/background_updates.py
matrix_admin_sdk/models/v1/delete_local_media.py
matrix_admin_sdk/models/v1/event_reports.py
matrix_admin_sdk/models/v1/federation.py
matrix_admin_sdk/models/v1/forward_extremities.py
matrix_admin_sdk/models/v1/querying_media.py
matrix_admin_sdk/models/v1/register_user.py
matrix_admin_sdk/models/v1/registration_tokens.py
matrix_admin_sdk/models/v1/rooms.py
matrix_admin_sdk/models/v1/server.py
matrix_admin_sdk-0.2.0b0.dist-info/LICENSE
matrix_admin_sdk-0.2.0b0.dist-info/WHEEL
matrix_admin_sdk-0.2.0b0.dist-info/METADATA
matrix_admin_sdk-0.2.0b0.dist-info/RECORD
