Metadata-Version: 2.1
Name: matrix-admin-sdk
Version: 0.2.0b0
Summary: Async wrapper for matrix.org admin API
Home-page: https://github.com/dmitriiweb/matrix-admin-sdk
Keywords: sdk,matrix,synapse
Author: Dmitrii Kurlov
Author-email: dmitriik@protonmail.com
Requires-Python: >=3.8,<3.11
Classifier: Development Status :: 4 - Beta
Classifier: License :: OSI Approved :: MIT License
Classifier: Operating System :: MacOS
Classifier: Operating System :: Microsoft :: Windows
Classifier: Operating System :: Unix
Classifier: Programming Language :: Python :: 3
Classifier: Programming Language :: Python :: 3.10
Classifier: Programming Language :: Python :: 3.8
Classifier: Programming Language :: Python :: 3.9
Classifier: Programming Language :: Python :: Implementation :: CPython
Requires-Dist: httpx (>=0.22.0,<0.23.0)
Project-URL: Documentation, https://dmitriiweb.github.io/matrix-admin-sdk
Project-URL: Repository, https://github.com/dmitriiweb/matrix-admin-sdk
